worldflow/__init__.py
worldflow/aws_handlers.py
worldflow/aws_setup.py
worldflow/decorators.py
worldflow/events.py
worldflow/fastapi_integration.py
worldflow/primitives.py
worldflow/retry.py
worldflow/runtime.py
worldflow/world.py
worldflow/cli/__init__.py
worldflow/cli/main.py
worldflow/worlds/__init__.py
worldflow/worlds/aws.py
worldflow/worlds/local.py
worldflow-0.1.3.dist-info/METADATA
worldflow-0.1.3.dist-info/WHEEL
worldflow-0.1.3.dist-info/entry_points.txt
worldflow-0.1.3.dist-info/licenses/LICENSE
worldflow-0.1.3.dist-info/RECORD
