Metadata-Version: 2.4
Name: worldflow
Version: 0.1.3
Summary: DX-first durable workflow orchestration for Python. Write normal async code, survive restarts, run anywhere.
Project-URL: Homepage, https://github.com/ptsadi/worldflow
Project-URL: Documentation, https://github.com/ptsadi/worldflow#readme
Project-URL: Repository, https://github.com/ptsadi/worldflow
Project-URL: Issues, https://github.com/ptsadi/worldflow/issues
Project-URL: Changelog, https://github.com/ptsadi/worldflow/blob/main/CHANGELOG.md
Author-email: Worldflow Contributors <worldflow@example.com>
License: MIT
License-File: LICENSE
Keywords: async,aws-lambda,durable-execution,event-sourcing,orchestration,serverless,temporal,workflow
Classifier: Development Status :: 4 - Beta
Classifier: Framework :: AsyncIO
Classifier: Intended Audience :: Developers
Classifier: License :: OSI Approved :: MIT License
Classifier: Programming Language :: Python :: 3
Classifier: Programming Language :: Python :: 3.11
Classifier: Programming Language :: Python :: 3.12
Classifier: Topic :: Software Development :: Libraries :: Python Modules
Classifier: Topic :: System :: Distributed Computing
Requires-Python: >=3.11
Requires-Dist: aiosqlite>=0.19.0
Requires-Dist: apscheduler>=3.10.0
Requires-Dist: click>=8.1.0
Requires-Dist: fastapi>=0.100.0
Requires-Dist: pydantic>=2.0.0
Requires-Dist: rich>=13.0.0
Requires-Dist: typing-extensions>=4.0.0
Requires-Dist: uvicorn>=0.23.0
Provides-Extra: aws
Requires-Dist: aioboto3>=12.0.0; extra == 'aws'
Requires-Dist: boto3>=1.28.0; extra == 'aws'
Provides-Extra: dev
Requires-Dist: mypy>=1.5.0; extra == 'dev'
Requires-Dist: pytest-asyncio>=0.21.0; extra == 'dev'
Requires-Dist: pytest>=7.4.0; extra == 'dev'
Requires-Dist: ruff>=0.1.0; extra == 'dev'
Provides-Extra: gcp
Requires-Dist: google-cloud-firestore>=2.12.0; extra == 'gcp'
Requires-Dist: google-cloud-pubsub>=2.18.0; extra == 'gcp'
